optexity/__init__.py
optexity/cli.py
optexity/exceptions.py
optexity/onepassword_integration.py
optexity/test.py
optexity/examples/__init__.py
optexity/examples/add_example.py
optexity/examples/download_pdf_url.py
optexity/examples/extract_price_stockanalysis.py
optexity/examples/file_upload.py
optexity/examples/i94.py
optexity/examples/i94_travel_history.py
optexity/examples/peachstate_medicaid.py
optexity/examples/supabase_login.py
optexity/inference/__init__.py
optexity/inference/child_process.py
optexity/inference/run_local.py
optexity/inference/agents/__init__.py
optexity/inference/agents/error_handler/__init__.py
optexity/inference/agents/error_handler/error_handler.py
optexity/inference/agents/error_handler/prompt.py
optexity/inference/agents/index_prediction/__init__.py
optexity/inference/agents/index_prediction/action_prediction_locator_axtree.py
optexity/inference/agents/index_prediction/prompt.py
optexity/inference/agents/select_value_prediction/__init__.py
optexity/inference/agents/select_value_prediction/prompt.py
optexity/inference/agents/select_value_prediction/select_value_prediction.py
optexity/inference/agents/two_fa_extraction/__init__.py
optexity/inference/agents/two_fa_extraction/prompt.py
optexity/inference/agents/two_fa_extraction/two_fa_extraction.py
optexity/inference/core/__init__.py
optexity/inference/core/logging.py
optexity/inference/core/run_assertion.py
optexity/inference/core/run_automation.py
optexity/inference/core/run_extraction.py
optexity/inference/core/run_interaction.py
optexity/inference/core/run_python_script.py
optexity/inference/core/run_two_fa.py
optexity/inference/core/interaction/__init__.py
optexity/inference/core/interaction/handle_agentic_task.py
optexity/inference/core/interaction/handle_check.py
optexity/inference/core/interaction/handle_click.py
optexity/inference/core/interaction/handle_command.py
optexity/inference/core/interaction/handle_hover.py
optexity/inference/core/interaction/handle_input.py
optexity-0.1.5.2.dist-info/licenses/LICENSE
optexity-0.1.5.2.dist-info/METADATA
optexity-0.1.5.2.dist-info/WHEEL
optexity-0.1.5.2.dist-info/entry_points.txt
optexity-0.1.5.2.dist-info/top_level.txt
optexity-0.1.5.2.dist-info/RECORD
