Metadata-Version: 2.4
Name: optexity
Version: 0.1.5.2
Summary: Optexity is a platform for building and running browser and computer agents.
Author-email: Optexity <founders@optexity.com>
Requires-Python: >=3.11
License-File: LICENSE
Requires-Dist: pydantic>=2
Requires-Dist: pydantic-settings
Requires-Dist: optexity-browser-use>=0.9.5
Requires-Dist: fastapi
Requires-Dist: httpx
Requires-Dist: aiofiles
Requires-Dist: async-lru
Requires-Dist: playwright
Requires-Dist: patchright
Requires-Dist: tokencost
Requires-Dist: onepassword-sdk
Provides-Extra: dev
Requires-Dist: black; extra == "dev"
Requires-Dist: isort; extra == "dev"
Requires-Dist: pre-commit; extra == "dev"
Dynamic: license-file
